Workbook

Sheet Dashboard
A1: Tableau de bord chantier
A2: Les indicateurs se mettent à jour automatiquement à partir des feuilles de saisie.
A4: Projet | D4: Code | G4: Budget prévu | J4: Dernière MAJ
A5: =Calculs!B2 | D5: =Calculs!B3 | G5: =Calculs!B4 | J5: =Calculs!B6
A8: Avancement réel | D8: Avancement cible | G8: Retard / avance | J8: Dépenses réelles | M8: Conso budget
A9: =Calculs!B7 | D9: =Calculs!B5 | G9: =Calculs!B19 | J9: =Calculs!B11 | M9: =Calculs!B12
A13: Effectif moyen | D13: Jours suivis | G13: Incidents total | J13: Non-conformités | M13: Incidents sécurité
A14: =Calculs!B8 | D14: =Calculs!B9 | G14: =Calculs!B13 | J14: =Calculs!B14 | M14: =Calculs!B15
A18: Lecture rapide | H18: Alerte budget
A19: =IF(Calculs!B7=0,"Aucun avancement saisi pour le moment.","Avancement actuel : "&TEXT(Calculs!B7,"0.0%")&" | Cible : "&TEXT(Calculs!B5,"0.0%")&" | Écart : "&TEXT(Calculs!B19,"0.0%")) | H19: =IF(Calculs!B12>1,"⚠ Dépenses supérieures au budget prévu.",IF(Calculs!B12>0.8,"Vigilance : plus de 80% du budget consommé.","Budget sous contrôle."))

Sheet Mode_emploi
A1: Mode d'emploi — fiche chantier automatisée
A2: Objectif : centraliser toutes les infos pour qu'un nouveau responsable reprenne le chantier sans perte d'information.
A4: 1. Commencer par la feuille Identification | C4: Renseigne le chantier, les dates, le budget et les objectifs d'avancement.
A6: 2. Saisir les acteurs | C6: Ajoute tous les intervenants, rôles et contacts clés.
A8: 3. Mettre à jour le Journal chaque jour | C8: Date, travaux réalisés, avancement %, effectif, météo et observations.
A10: 4. Saisir chaque livraison de matériaux | C10: Une ligne par livraison ou mouvement important.
A12: 5. Enregistrer toutes les dépenses | C12: Utilise la feuille Finances pour garder la traçabilité budgétaire.
A14: 6. Déclarer les incidents et la sécurité | C14: Aucun problème ne doit rester oral : tout doit être écrit.
A16: 7. Lire le Dashboard | C16: Les indicateurs se mettent à jour automatiquement.
A20: Exemple déjà rempli : utilise-le comme modèle, puis remplace les données chantier ligne par ligne. | B20: Aucun paiement ou validation chantier si la fiche n'est pas à jour.

Sheet Identification
A1: Fiche d'identification du chantier
A2: Les cellules bleues sont à remplir manuellement.
A4: Nom du projet | B4: Construction villa duplex R+1 – Cocody Angré
A6: Code chantier | B6: CH-ANGRE-2026-001
A8: Type de chantier | B8: Construction neuve – villa duplex
A10: Localisation précise | B10: Abidjan, Cocody Angré 8e tranche, lot 245
A12: Client / Maître d'ouvrage | B12: Famille Konan / M. Jean Konan
A14: Date de démarrage | B14: 46056
A16: Date prévisionnelle de fin | B16: 46233
A18: Budget global prévu (FCFA) | B18: 85000000
A20: Avancement cible à date (%) | B20: 42
A22: Chef de chantier principal | B22: Kouassi Yao
A24: Conducteur de travaux
A26: Directeur technique

Sheet Acteurs
A1: Acteurs du chantier
A2: Renseigne l'encadrement, la main d'œuvre et les sous-traitants.
A4: Rôle | B4: Nom complet | C4: Contact | D4: Entreprise / Fonction | E4: Présence active | F4: Observations
A5: Directeur Technique | B5: M. Yao N'Dri | C5: 07 08 09 10 11 | D5: Direction Technique | E5: Oui | F5: Supervision générale
A6: Conducteur de travaux | B6: M. Tano Serge | C6: 01 02 03 04 05 | D6: Conduite des travaux | E6: Oui | F6: Présence quotidienne
A7: Chef de chantier | B7: M. Kouassi Yao | C7: 05 44 55 66 77 | D7: Chef de chantier | E7: Oui | F7: Responsable exécution
A8: Maçon principal | B8: M. Koffi Hervé | C8: 07 77 88 99 00 | D8: Maçonnerie | E8: Oui | F8: Équipe gros œuvre
A9: Ferrailleur | B9: M. Bamba Issa | C9: 01 66 77 88 99 | D9: Ferraillage | E9: Oui | F9: Armatures semelles et poteaux
A10: Électricien | B10: M. Traoré Mamadou | C10: 05 11 22 33 44 | D10: Sous-traitant électricité | E10: Non | F10: Intervention prévue en phase 2
A11: Plombier | B11: M. N'Guessan Alain | C11: 07 21 31 41 51 | D11: Sous-traitant plomberie | E11: Non | F11: Intervention ultérieure

Sheet Journal
A1: Journal de chantier
A2: Une ligne par jour. L'avancement saisi ici alimente le tableau de bord.
A4: Date | B4: Travaux réalisés | C4: Avancement cumulé (%) | D4: Effectif présent | E4: Matériel utilisé | F4: Météo | G4: Blocage / observation | H4: Responsable saisie
A5: 46056 | B5: Installation de chantier, nettoyage du site et implantation | C5: 3 | D5: 8 | E5: Niveau, piquets, pelle, brouette | F5: Soleil | G5: RAS | H5: Tano Serge
A6: 46061 | B6: Terrassement et fouilles des semelles | C6: 8 | D6: 11 | E6: Pelle, pioche, cordeau | F6: Nuageux | G6: Sol plus dur que prévu sur zone arrière | H6: Kouassi Yao
A7: 46068 | B7: Ferraillage semelles et longrines | C7: 15 | D7: 12 | E7: Coupeuse, ligature, tenaille | F7: Soleil | G7: Attente partielle de livraison fer HA12 | H7: Kouassi Yao
A8: 46073 | B8: Coulage béton de propreté et semelles | C8: 22 | D8: 14 | E8: Bétonnière, vibreur | F8: Soleil | G8: RAS | H8: Tano Serge
A9: 46081 | B9: Élévation soubassement et remblai intérieur | C9: 28 | D9: 13 | E9: Brouette, dame manuelle | F9: Soleil | G9: RAS | H9: Kouassi Yao
A10: 46086 | B10: Montage poteaux RDC et coffrage poutres | C10: 34 | D10: 15 | E10: Scie, marteau, serre-joints | F10: Nuageux | G10: Besoin complément bois de coffrage | H10: Kouassi Yao
A11: 46093 | B11: Coulage poteaux et poutres RDC | C11: 39 | D11: 16 | E11: Bétonnière, vibreur | F11: Soleil | G11: RAS | H11: Tano Serge
A12: 46097 | B12: Préparation dalle RDC et réservations techniques | C12: 41 | D12: 15 | E12: Treillis, planches, fil à ligaturer | F12: Soleil | G12: Prévoir coordination plombier avant coulage | H12: Kouassi Yao

Sheet Materiaux
A1: Suivi des matériaux
A2: Saisir chaque livraison, sortie importante ou contrôle de stock.
A4: Date | B4: Type matériau | C4: Quantité | D4: Unité | E4: Mouvement | F4: Fournisseur | G4: Réception OK | H4: Valeur estimée (FCFA) | I4: Observation
A5: 46057 | B5: Ciment | C5: 200 | D5: sacs | E5: Entrée | F5: CIMIVOIRE | G5: Oui | H5: 1900000 | I5: Première livraison
A6: 46059 | B6: Sable | C6: 18 | D6: m3 | E6: Entrée | F6: Carrière Bingerville | G6: Oui | H6: 450000 | I6: Pour fouilles et béton
A7: 46060 | B7: Gravier | C7: 16 | D7: m3 | E7: Entrée | F7: Carrière Anyama | G7: Oui | H7: 520000 | I7: Granulats 5/15
A8: 46063 | B8: Fer | C8: 3.5 | D8: tonnes | E8: Entrée | F8: SOTACI | G8: Oui | H8: 3150000 | I8: HA8, HA10, HA12
A9: 46071 | B9: Bois | C9: 1.2 | D9: lot | E9: Entrée | F9: Bois Service | G9: Oui | H9: 780000 | I9: Coffrage
A10: 46075 | B10: Ciment | C10: 120 | D10: sacs | E10: Sortie | F10: Consommation chantier | G10: Oui | H10: 1140000 | I10: Semelles + longrines
A11: 46082 | B11: Briques | C11: 4500 | D11: unités | E11: Entrée | F11: Briqueterie Akoupé | G11: Oui | H11: 1350000 | I11: Élévation RDC
A12: 46089 | B12: Fer | C12: 0.8 | D12: tonnes | E12: Sortie | F12: Consommation chantier | G12: Oui | H12: 720000 | I12: Poteaux/poutres RDC

Sheet Finances
A1: Suivi financier
A2: Toutes les dépenses chantier doivent être enregistrées ici.
A4: Date | B4: Catégorie | C4: Désignation | D4: Montant prévu (FCFA) | E4: Montant réel (FCFA) | F4: Écart (FCFA) | G4: Statut paiement | H4: Bénéficiaire / fournisseur | I4: Observation
A5: 46056 | B5: Installation | C5: Base vie et sécurisation site | D5: 850000 | E5: 900000 | F5: =IF(OR(D5="",E5=""),"",E5-D5) | G5: Payé | H5: Entreprise BTP Papa | I5: Dépense de démarrage
A6: 46058 | B6: Main d'œuvre | C6: Terrassement et fouilles | D6: 650000 | E6: 650000 | F6: =IF(OR(D6="",E6=""),"",E6-D6) | G6: Payé | H6: Équipe terrassement | I6: Conforme au prévu
A7: 46063 | B7: Matériaux | C7: Achat fer à béton | D7: 3200000 | E7: 3150000 | F7: =IF(OR(D7="",E7=""),"",E7-D7) | G7: Payé | H7: SOTACI | I7: Léger gain négocié
A8: 46065 | B8: Transport | C8: Évacuation déblais + livraison sable | D8: 300000 | E8: 365000 | F8: =IF(OR(D8="",E8=""),"",E8-D8) | G8: Payé | H8: Transports Kouamé | I8: Surcoût carburant
A9: 46073 | B9: Main d'œuvre | C9: Coulage semelles et longrines | D9: 700000 | E9: 760000 | F9: =IF(OR(D9="",E9=""),"",E9-D9) | G9: Partiel | H9: Équipe gros œuvre | I9: Solde à payer
A10: 46081 | B10: Matériaux | C10: Achat briques | D10: 1400000 | E10: 1350000 | F10: =IF(OR(D10="",E10=""),"",E10-D10) | G10: Payé | H10: Briqueterie Akoupé | I10: Conforme
A11: 46088 | B11: Équipements | C11: Location bétonnière + vibreur | D11: 250000 | E11: 250000 | F11: =IF(OR(D11="",E11=""),"",E11-D11) | G11: Payé | H11: LocaMat CI | I11: RAS
A12: 46095 | B12: Main d'œuvre | C12: Coffrage et dalle RDC | D12: 900000 | E12: 0 | F12: =IF(OR(D12="",E12=""),"",E12-D12) | G12: En attente | H12: Équipe coffrage | I12: Paiement après validation DT
F13: =IF(OR(D13="",E13=""),"",E13-D13)
F14: =IF(OR(D14="",E14=""),"",E14-D14)
F15: =IF(OR(D15="",E15=""),"",E15-D15)
F16: =IF(OR(D16="",E16=""),"",E16-D16)
F17: =IF(OR(D17="",E17=""),"",E17-D17)
F18: =IF(OR(D18="",E18=""),"",E18-D18)
F19: =IF(OR(D19="",E19=""),"",E19-D19)
F20: =IF(OR(D20="",E20=""),"",E20-D20)
F21: =IF(OR(D21="",E21=""),"",E21-D21)
F22: =IF(OR(D22="",E22=""),"",E22-D22)
F23: =IF(OR(D23="",E23=""),"",E23-D23)
F24: =IF(OR(D24="",E24=""),"",E24-D24)
... F404: =IF(OR(D404="",E404=""),"",E404-D404)

Sheet Equipements
A1: Matériel & équipements
A2: Suivi de l'état des équipements présents sur site.
A4: Équipement | B4: Quantité | C4: État | D4: Dernier contrôle | E4: Panne / anomalie | F4: Action requise | G4: Responsable
A5: Bétonnière | B5: 1 | C5: Bon | D5: 46091 | E5: Aucune | F5: Entretien hebdomadaire | G5: Chef de chantier
A6: Vibreur | B6: 1 | C6: Bon | D6: 46091 | E6: Aucune | F6: Contrôle câble alimentation | G6: Chef de chantier
A7: Brouettes | B7: 4 | C7: Moyen | D7: 46093 | E7: 1 roue usée | F7: Remplacement roue sous 3 jours | G7: Magasinier
A8: Échelles | B8: 2 | C8: Bon | D8: 46093 | E8: Aucune | F8: RAS | G8: Chef de chantier
A9: Groupe électrogène | B9: 1 | C9: Moyen | D9: 46090 | E9: Démarrage difficile | F9: Vidange + bougie | G9: Mécanicien

Sheet Incidents
A1: Incidents / problèmes chantier
A2: Tout incident doit être enregistré pour éviter les transmissions orales incomplètes.
A4: Date | B4: Type incident | C4: Description | D4: Impact | E4: Solution apportée | F4: Responsable | G4: Date clôture | H4: Statut
A5: 46062 | B5: Retard | C5: Retard de livraison d'une partie du fer HA12 | D5: Décalage de 1 jour sur ferraillage | E5: Réajustement planning + relance fournisseur | F5: Conducteur travaux | G5: 46063 | H5: Clôturé
A6: 46087 | B6: Rupture stock | C6: Bois de coffrage insuffisant pour zone escalier | D6: Ralentissement coffrage | E6: Commande complémentaire immédiate | F6: Chef de chantier | G6: 46088 | H6: Clôturé
A7: 46092 | B7: Panne | C7: Brouette n°3 hors service | D7: Manutention ralentie | E7: Réparation roue | F7: Magasinier | G7: 46093 | H7: Clôturé

Sheet Qualite
A1: Qualité & contrôle
A2: Saisir les contrôles, écarts et corrections.
A4: Date | B4: Contrôle effectué | C4: Non-conformité | D4: Correction / action | E4: Responsable | F4: Statut
A5: 46073 | B5: Contrôle dosage béton semelles | C5: Aucune | D5: Validation avant coulage | E5: DT | F5: Conforme
A6: 46086 | B6: Vérification aplomb poteaux RDC | C6: Écart léger sur 1 poteau | D6: Reprise coffrage avant coulage | E6: Conducteur travaux | F6: Corrigé
A7: 46097 | B7: Contrôle réservations techniques dalle | C7: Aucune | D7: Coordination plomberie notée | E7: DT | F7: Conforme

Sheet Securite
A1: Sécurité chantier
A2: Saisir les incidents sécurité, manquements et mesures prises.
A4: Date | B4: Type sécurité | C4: Description | D4: Mesures prises | E4: EPI disponibles | F4: Responsable | G4: Statut
A5: 46057 | B5: EPI manquant | C5: 2 ouvriers sans gants à l'ouverture du site | D5: Rappel consignes + distribution EPI | E5: Casques, gants, bottes | F5: Chef de chantier | G5: Traité
A6: 46074 | B6: Non-respect consigne | C6: Zone coulage encombrée | D6: Nettoyage immédiat + balisage | E6: Casques, bottes | F6: Chef de chantier | G6: Traité
A7: 46094 | B7: Quasi-accident | C7: Glissade sans blessure près de la zone humide | D7: Ajout sable sec + signalisation | E7: Casques, gants, bottes, gilets | F7: Conducteur travaux | G7: Traité

Sheet Parametres
A1: Paramètres & listes déroulantes
A2: Modifie cette feuille seulement si tu veux changer les listes proposées.
A4: Météo | C4: Réception | E4: Statut paiement | G4: Etat équipement | I4: Type incident | K4: Type sécurité | M4: Matériaux courants
A5: Soleil | C5: Oui | E5: Payé | G5: Bon | I5: Retard | K5: EPI manquant | M5: Ciment
A6: Nuageux | C6: Non | E6: En attente | G6: Moyen | I6: Accident | K6: Accident | M6: Fer
A7: Pluie | E7: Partiel | G7: Mauvais | I7: Litige | K7: Quasi-accident | M7: Sable
A8: Orage | G8: Hors service | I8: Rupture stock | K8: Non-respect consigne | M8: Gravier
A9: Vent fort | I9: Panne | K9: RAS | M9: Briques
I10: Autre | M10: Peinture
M11: Bois
M12: Carrelage
M13: Autre

Sheet Calculs
A1: Clé | B1: Valeur | D1: Date journal | E1: Avancement % | G1: Statut paiement | H1: Nombre | J1: Type incident | K1: Nombre | M1: Type matériau | N1: Qté
A2: Nom projet | B2: =Identification!B4 | D2: =Journal!A5 | E2: =Journal!C5 | G2: Payé | H2: =COUNTIF(Finances!G5:G404,"Payé") | J2: Retard | K2: =COUNTIF(Incidents!B5:B204,"Retard") | M2: Ciment | N2: =SUMIF(Materiaux!B5:B404,"Ciment",Materiaux!C5:C404)
A3: Code chantier | B3: =Identification!B6 | D3: =Journal!A6 | E3: =Journal!C6 | G3: En attente | H3: =COUNTIF(Finances!G5:G404,"En attente") | J3: Accident | K3: =COUNTIF(Incidents!B5:B204,"Accident") | M3: Fer | N3: =SUMIF(Materiaux!B5:B404,"Fer",Materiaux!C5:C404)
A4: Budget prévu | B4: =IFERROR(Identification!B18,0) | D4: =Journal!A7 | E4: =Journal!C7 | G4: Partiel | H4: =COUNTIF(Finances!G5:G404,"Partiel") | J4: Litige | K4: =COUNTIF(Incidents!B5:B204,"Litige") | M4: Sable | N4: =SUMIF(Materiaux!B5:B404,"Sable",Materiaux!C5:C404)
A5: Avancement cible | B5: =IFERROR(Identification!B20,0) | D5: =Journal!A8 | E5: =Journal!C8 | J5: Rupture stock | K5: =COUNTIF(Incidents!B5:B204,"Rupture stock") | M5: Gravier | N5: =SUMIF(Materiaux!B5:B404,"Gravier",Materiaux!C5:C404)
A6: Dernière date journal | B6: =IFERROR(MAX(Journal!A5:A404),"") | D6: =Journal!A9 | E6: =Journal!C9 | J6: Panne | K6: =COUNTIF(Incidents!B5:B204,"Panne") | M6: Briques | N6: =SUMIF(Materiaux!B5:B404,"Briques",Materiaux!C5:C404)
A7: Avancement réel | B7: =IFERROR(LOOKUP(2,1/(Journal!C5:C404<>""),Journal!C5:C404),0) | D7: =Journal!A10 | E7: =Journal!C10 | J7: Autre | K7: =COUNTIF(Incidents!B5:B204,"Autre") | M7: Peinture | N7: =SUMIF(Materiaux!B5:B404,"Peinture",Materiaux!C5:C404)
A8: Effectif moyen | B8: =IFERROR(AVERAGEIF(Journal!D5:D404,">0"),0) | D8: =Journal!A11 | E8: =Journal!C11 | M8: Bois | N8: =SUMIF(Materiaux!B5:B404,"Bois",Materiaux!C5:C404)
A9: Nb jours suivis | B9: =COUNT(Journal!A5:A404) | D9: =Journal!A12 | E9: =Journal!C12 | M9: Carrelage | N9: =SUMIF(Materiaux!B5:B404,"Carrelage",Materiaux!C5:C404)
A10: Total dépenses prévues | B10: =SUM(Finances!D5:D404) | D10: =Journal!A13 | E10: =Journal!C13 | M10: Autre | N10: =SUMIF(Materiaux!B5:B404,"Autre",Materiaux!C5:C404)
A11: Total dépenses réelles | B11: =SUM(Finances!E5:E404) | D11: =Journal!A14 | E11: =Journal!C14
A12: Taux conso budget | B12: =IFERROR(B10/B3,0) | D12: =Journal!A15 | E12: =Journal!C15
A13: Nb incidents | B13: =COUNT(Incidents!A5:A204) | D13: =Journal!A16 | E13: =Journal!C16
A14: Nb non conformités | B14: =COUNTIF(Qualite!C5:C204,"<>") | D14: =Journal!A17 | E14: =Journal!C17
A15: Nb incidents sécurité | B15: =COUNT(Securite!A5:A204) | D15: =Journal!A18 | E15: =Journal!C18
A16: Nb livraisons matériaux | B16: =COUNT(Materiaux!A5:A404) | D16: =Journal!A19 | E16: =Journal!C19
A17: Valeur matériaux | B17: =SUM(Materiaux!H5:H404) | D17: =Journal!A20 | E17: =Journal!C20
A18: Écart budget | B18: =B10-B3 | D18: =Journal!A21 | E18: =Journal!C21
A19: Retard vs cible | B19: =B6-B4 | D19: =Journal!A22 | E19: =Journal!C22
D20: =Journal!A23 | E20: =Journal!C23
D21: =Journal!A24 | E21: =Journal!C24
D22: =Journal!A25 | E22: =Journal!C25
D23: =Journal!A26 | E23: =Journal!C26
D24: =Journal!A27 | E24: =Journal!C27
D25: =Journal!A28 | E25: =Journal!C28
D26: =Journal!A29 | E26: =Journal!C29
D27: =Journal!A30 | E27: =Journal!C30
D28: =Journal!A31 | E28: =Journal!C31
D29: =Journal!A32 | E29: =Journal!C32
D30: =Journal!A33 | E30: =Journal!C33
D31: =Journal!A34 | E31: =Journal!C34
... D401: =Journal!A404 | E401: =Journal!C404
